circa/__init__.py
circa/utils.py
circa/alg/__init__.py
circa/alg/base.py
circa/alg/common.py
circa/alg/correlation.py
circa/alg/dfs.py
circa/alg/evt.py
circa/alg/random_walk.py
circa/alg/ci/__init__.py
circa/alg/ci/anm.py
circa/alg/ci/base.py
circa/alg/ci/gmm/__init__.py
circa/alg/ci/gmm/base.py
circa/alg/ci/gmm/mdn.py
circa/alg/ci/gmm/prob_rf.py
circa/alg/invariant_network/__init__.py
circa/alg/invariant_network/crd.py
circa/alg/invariant_network/enmf.py
circa/experiment/__init__.py
circa/experiment/__main__.py
circa/experiment/comparison/__init__.py
circa/experiment/comparison/models.py
circa/experiment/comparison/utils.py
circa/experiment/simulation/__init__.py
circa/experiment/simulation/robustness.py
circa/experiment/simulation/scorer.py
circa/graph/__init__.py
circa/graph/base.py
circa/graph/common.py
circa/graph/pcts.py
circa/graph/structural.py
circa/graph/r/__init__.py
circa/graph/r/causal.R
circa/graph/r/utils.py
circa/model/__init__.py
circa/model/case.py
circa/model/data_loader.py
circa/model/graph.py
circa_clue-0.1.1.dist-info/LICENSE
circa_clue-0.1.1.dist-info/METADATA
circa_clue-0.1.1.dist-info/WHEEL
circa_clue-0.1.1.dist-info/top_level.txt
circa_clue-0.1.1.dist-info/RECORD
