Metadata-Version: 2.1
Name: circa-clue
Version: 0.1.1
Summary: Causal Inference-based Root Cause Analysis
Home-page: https://github.com/NetManAIOps/CIRCA
Author: limjcst
Author-email: limjcst@163.com
License: BSD 3-Clause License
Classifier: Programming Language :: Python :: 3.7
Classifier: Operating System :: OS Independent
Classifier: License :: OSI Approved :: BSD License
License-File: LICENSE
Requires-Dist: ads-evt
Requires-Dist: bayesian-changepoint-detection
Requires-Dist: dataclasses
Requires-Dist: networkx
Requires-Dist: numpy
Requires-Dist: pandas
Requires-Dist: pingouin
Requires-Dist: pytorch-lightning
Requires-Dist: PyYAML
Requires-Dist: rpy2
Requires-Dist: scipy
Requires-Dist: scikit-learn
Requires-Dist: tigramite
Requires-Dist: torch
